sumonitor/__init__.py
sumonitor/main.py
sumonitor/data/__init__.py
sumonitor/data/log_reader.py
sumonitor/data/pricing.py
sumonitor/session/__init__.py
sumonitor/session/session_data.py
sumonitor/session/session_tracker.py
sumonitor/terminal/__init__.py
sumonitor/terminal/terminal_handler.py
sumonitor-0.1.0.dist-info/licenses/LICENSE
sumonitor-0.1.0.dist-info/METADATA
sumonitor-0.1.0.dist-info/WHEEL
sumonitor-0.1.0.dist-info/entry_points.txt
sumonitor-0.1.0.dist-info/top_level.txt
sumonitor-0.1.0.dist-info/RECORD
