Metadata-Version: 2.4
Name: sumonitor
Version: 0.1.0
Summary: Real-time token and cost monitoring overlay for Claude Code CLI with session tracking
Author-email: Srivathsan Sivakumar <sri.skumar05@gmail.com>
Maintainer-email: Srivathsan Sivakumar <sri.skumar05@gmail.com>
License: MIT
Project-URL: homepage, https://github.com/SrivathsanSivakumar/simple-usage-monitor
Project-URL: repository, https://github.com/SrivathsanSivakumar/simple-usage-monitor.git
Project-URL: documentation, https://github.com/SrivathsanSivakumar/simple-usage-monitor#readme
Project-URL: issues, https://github.com/SrivathsanSivakumar/simple-usage-monitor/issues
Project-URL: changelog, https://github.com/SrivathsanSivakumar/simple-usage-monitor/blob/main/CHANGELOG.md
Keywords: ai,anthropic,claude,claude-code,cost-tracking,developer-tools,monitoring,terminal,token-usage,usage-tracking
Classifier: Development Status :: 4 - Beta
Classifier: Environment :: Console
Classifier: Intended Audience :: Developers
Classifier: Topic :: Software Development :: Libraries :: Python Modules
Classifier: Topic :: System :: Monitoring
Classifier: Topic :: Terminals
Classifier: Topic :: Utilities
Classifier: Programming Language :: Python :: 3
Classifier: Programming Language :: Python :: 3 :: Only
Classifier: Programming Language :: Python :: 3.8
Classifier: Programming Language :: Python :: 3.9
Classifier: Programming Language :: Python :: 3.10
Classifier: Programming Language :: Python :: 3.11
Classifier: Programming Language :: Python :: 3.12
Classifier: License :: OSI Approved :: MIT License
Classifier: Operating System :: OS Independent
Classifier: Operating System :: POSIX :: Linux
Classifier: Operating System :: MacOS
Classifier: Typing :: Typed
Requires-Python: >=3.8
License-File: LICENSE
Requires-Dist: pexpect>=4.8.0
Provides-Extra: dev
Requires-Dist: pytest>=8.0.0; extra == "dev"
Requires-Dist: pytest-cov>=5.0.0; extra == "dev"
Requires-Dist: pytest-mock>=3.14.0; extra == "dev"
Requires-Dist: pytest-timeout>=2.3.0; extra == "dev"
Requires-Dist: pytest-xdist>=3.6.0; extra == "dev"
Requires-Dist: freezegun>=1.5.0; extra == "dev"
Requires-Dist: build>=0.10.0; extra == "dev"
Requires-Dist: twine>=4.0.0; extra == "dev"
Provides-Extra: test
Requires-Dist: pytest>=8.0.0; extra == "test"
Requires-Dist: pytest-cov>=5.0.0; extra == "test"
Requires-Dist: pytest-mock>=3.14.0; extra == "test"
Requires-Dist: pytest-timeout>=2.3.0; extra == "test"
Requires-Dist: freezegun>=1.5.0; extra == "test"
Requires-Dist: pytest-xdist>=3.6.0; extra == "test"
Dynamic: license-file
